Metadata-Version: 2.1
Name: ja-fib-py
Version: 0.0.3
Summary: Calculates a Fibonacci number
Home-page: https://github.com/iberiaz9/flitton-fib-py
Author: Jose Alvarado
Author-email: alvarado.ja53@gmail.com
License: UNKNOWN
Platform: UNKNOWN
Classifier: Development Status :: 4 - Beta
Classifier: Programming Language :: Python :: 3
Classifier: Operating System :: OS Independent
Requires-Python: >=3
Provides-Extra: server
